LICENSE
README.rst
setup.py
corona_starken.egg-info/PKG-INFO
corona_starken.egg-info/SOURCES.txt
corona_starken.egg-info/dependency_links.txt
corona_starken.egg-info/requires.txt
corona_starken.egg-info/top_level.txt
starken/connector.py
starken/handler.py
starken/settings.py