Metadata-Version: 2.1
Name: corona-starken
Version: 1.0.8
Summary: Django Starken Integration
Home-page: https://gitlab.com/linets-projects/python-libraries/django-starken/
Author: Corona Development Team
Author-email: rolguin@corona.cl
License: MIT
Platform: UNKNOWN
Requires-Python: >=3.7
License-File: LICENSE
